{
  "project_info": {
    "project_number": "970271030659",
    "project_id": "adith-intern",
    "storage_bucket": "adith-intern.appspot.com"
  },
  "client": [
    {
      "client_info": {
        "mobilesdk_app_id": "1:970271030659:android:1f1c6ebaf960ee616a8ab6",
        "android_client_info": {
          "package_name": "com.example.login_screen"
        }
      },
      "oauth_client": [
        {
          "client_id": "970271030659-6am9dp1hi6e70qlu9udme40piv8d9n8f.apps.googleusercontent.com",
          "client_type": 3
        }
      ],
      "api_key": [
        {
          "current_key": "AIzaSyAqqty0Yi_iRO2gjGgjKDUuwgbmUx81ARI"
        }
      ],
      "services": {
        "appinvite_service": {
          "other_platform_oauth_client": [
            {
              "client_id": "970271030659-6am9dp1hi6e70qlu9udme40piv8d9n8f.apps.googleusercontent.com",
              "client_type": 3
            }
          ]
        }
      }
    }
  ],
  "configuration_version": "1"
}